surfnet/__init__.py
surfnet/captcha_solver.py
surfnet/scraper.py
surfnet/system_profiler.py
surfnet-0.2.0.dist-info/licenses/LICENSE
surfnet-0.2.0.dist-info/METADATA
surfnet-0.2.0.dist-info/WHEEL
surfnet-0.2.0.dist-info/top_level.txt
surfnet-0.2.0.dist-info/RECORD
