Metadata-Version: 2.4
Name: surfnet
Version: 0.2.0
Summary: A powerful web scraping package with integrated search, captcha handling, and hardware optimization
Home-page: https://github.com/libdo96/surfnet
Author: Dead Depth
Author-email: transformtrails@gmail.com
Keywords: web scraping,search,captcha,crawler,parallel processing,gpu acceleration,high throughput
Classifier: Development Status :: 4 - Beta
Classifier: Intended Audience :: Developers
Classifier: License :: OSI Approved :: MIT License
Classifier: Programming Language :: Python :: 3
Classifier: Programming Language :: Python :: 3.7
Classifier: Programming Language :: Python :: 3.8
Classifier: Programming Language :: Python :: 3.9
Classifier: Programming Language :: Python :: 3.10
Classifier: Topic :: Internet :: WWW/HTTP :: Indexing/Search
Classifier: Topic :: Software Development :: Libraries :: Python Modules
Requires-Python: >=3.7
License-File: LICENSE
Requires-Dist: duckduckgo-search>=4.1.1
Requires-Dist: beautifulsoup4>=4.12.2
Requires-Dist: requests>=2.31.0
Requires-Dist: urllib3>=2.0.7
Requires-Dist: tqdm>=4.66.1
Requires-Dist: playwright>=1.42.0
Requires-Dist: concurrent-futures-extra>=1.0.2
Requires-Dist: fake-useragent>=1.4.0
Requires-Dist: undetected-playwright>=0.0.4
Requires-Dist: pypasser>=0.0.5
Requires-Dist: pillow>=10.0.0
Requires-Dist: SpeechRecognition>=3.10.0
Requires-Dist: pydub>=0.25.1
Requires-Dist: psutil>=5.9.0
Requires-Dist: GPUtil>=1.4.0
Requires-Dist: ray>=2.9.0
Dynamic: author
Dynamic: author-email
Dynamic: classifier
Dynamic: description
Dynamic: description-content-type
Dynamic: home-page
Dynamic: keywords
Dynamic: license-file
Dynamic: requires-dist
Dynamic: requires-python
Dynamic: summary
